git_jira_stats/__init__.py
git_jira_stats/main.py
git_jira_stats/test_main.py
git_jira_stats-0.1.0.dist-info/entry_points.txt
git_jira_stats-0.1.0.dist-info/WHEEL
git_jira_stats-0.1.0.dist-info/METADATA
git_jira_stats-0.1.0.dist-info/RECORD
