Metadata-Version: 2.1
Name: git-jira-stats
Version: 0.1.0
Summary: 
Author: Mikhail Putilov
Author-email: Mikhail.Putilov@dimoco.eu
Requires-Python: >=3.9,<4.0
Classifier: Programming Language :: Python :: 3
Classifier: Programming Language :: Python :: 3.10
Classifier: Programming Language :: Python :: 3.9
Requires-Dist: fire (>=0.4.0,<0.5.0)
Requires-Dist: jsonpickle (>=3.0.0,<4.0.0)
